{
    "GENRES": [
        {
            "genre": "Beat'em Up",
            "description": "Los clasicos de 'Yo contra el barrio'",
            "img": "/imgs/Capcom.avif",
            "alt": "Imagen de Beat'em Up",
            "link": "generos/Beat'em Up",
            "JUEGOS": [
                {
                    "title": "Final Fight",
                    "description": "",
                    "img": "/imgs/finals.avif",
                    "alt": "Portada Final Fight",
                    "link": "generos/juegos/final-fight"
                },
                {
                    "title": "Teenage Mutant Ninja Turtles",
                    "description": "",
                    "img": "/imgs/turtles.avif",
                    "alt": "Portada Teenage Mutant Ninja Turtles",
                    "link": "generos/juegos/"
                },
                {
                    "title": "Golden Axe",
                    "description": "",
                    "img": "/imgs/golden.avif",
                    "alt": "Portada Golden Axe",
                    "link": "generos/juegos/golden-axe"
                }
            ]
        },
        {
            "genre": "Run and Gun",
            "description": "¡Embárcate en una frenética carrera de balas y acción!",
            "img": "/imgs/blazing.avif",
            "alt": "Imagen de Run and Gun",
            "link": "generos/Run and Gun",
            "JUEGOS": [
                {
                    "title": "Sunset Riders",
                    "description": "",
                    "img": "/imgs/sunset.avif",
                    "alt": "Portada Sunset Riders",
                    "link": "generos/juegos/sunsetriders"
                },
                {
                    "title": "Metal Slug X",
                    "description": "",
                    "img": "/imgs/metalx.avif",
                    "alt": "Portada Metal Slug X",
                    "link": "generos/juegos/metal-slug-x"
                },
                {
                    "title": "Gunstar Heroes",
                    "description": "",
                    "img": "/imgs/gunstar.avif",
                    "alt": "Portada Gunstar Heroes",
                    "link": "generos/juegos/gunstar-heroes"
                }
            ]
        },
        {
            "genre": "Shoot'em Up",
            "description": "¡Libera un vendaval de balas y enfrenta el caos enérgico!",
            "img": "/imgs/shootem.avif",
            "alt": "Imagen de Shoot'em Up",
            "link": "generos/Shoot'em Up",
            "JUEGOS": [
                {
                    "title": "Blazing Start",
                    "description": "",
                    "img": "/imgs/blazin.avif",
                    "alt": "Portada Blazing Start",
                    "link": "generos/juegos/blazing-start"
                },
                {
                    "title": "Radiant Silvergun",
                    "description": "",
                    "img": "/imgs/radiant.avif",
                    "alt": "Portada Radiant Silvergun",
                    "link": "generos/juegos/radiant-silvergun"
                },
                {
                    "title": "Aero Fighters",
                    "description": "",
                    "img": "/imgs/aero.avif",
                    "alt": "Portada Aero Fighters",
                    "link": "generos/juegos/aero-fighters"
                }
            ]
        },
        {
            "genre": "Fighting",
            "description": "Domina la arena con los clasicos de la lucha",
            "img": "/imgs/fighting.avif",
            "alt": "Imagen de Fighting",
            "link": "generos/Fighting",
            "JUEGOS": [
                {
                    "title": "Street Fighter III",
                    "description": "",
                    "img": "/imgs/sfiii.avif",
                    "alt": "Portada Street Fighter III",
                    "link": "generos/juegos/street-fighter-iii"
                },
                {
                    "title": "Darkstalker",
                    "description": "",
                    "img": "/imgs/darkstalker.avif",
                    "alt": "Portada Darkstalker",
                    "link": "generos/juegos/darkstalker"
                },
                {
                    "title": "Garou Mark of the Wolves",
                    "description": "",
                    "img": "/imgs/garou.avif",
                    "alt": "Portada Garou Mark of the Wolves",
                    "link": "generos/juegos/garou-mark-of-the-wolves"
                }
            ]
        }
    ]
}